crams_log/__init__.py
crams_log/admin.py
crams_log/apps.py
crams_log/asgi.py
crams_log/log_process.py
crams_log/models.py
crams_log/settings.py
crams_log/test_settings.py
crams_log/urls.py
crams_log/views.py
crams_log/wsgi.py
crams_log/constants/__init__.py
crams_log/constants/log_actions.py
crams_log/constants/log_types.py
crams_log/log_events/__init__.py
crams_log/log_events/base.py
crams_log/log_events/login.py
crams_log/log_events/project.py
crams_log/log_events/provision.py
crams_log/migrations/0001_initial.py
crams_log/migrations/0002_userlog.py
crams_log/migrations/__init__.py
crams_log/serializers/__init__.py
crams_log/serializers/cram_log_sz.py
crams_log/serializers/event_log.py
crams_log/templates/__init__.py
crams_log/templates/swagger-ui.html
crams_log/utils/__init__.py
crams_log/utils/lookup_utils.py
crams_log/utils/validation_utils.py
crams_log-1.0.0.dist-info/METADATA
crams_log-1.0.0.dist-info/WHEEL
crams_log-1.0.0.dist-info/top_level.txt
crams_log-1.0.0.dist-info/RECORD
